[{"content":"","href":"/","title":"Home"},{"content":"","href":"/jupyter/","title":"Jupyter"},{"content":"","href":"/other/","title":"Other"},{"content":"","href":"/science/","title":"Science"},{"content":"","href":"/software/","title":"Software"},{"content":"Finally starting a blog.\nThank you to Letitia Portella and Saul Shanabrook for pushing me to make it happened.\n","href":"/other/first-post/","title":"Introducing my new blog"},{"content":"","href":"/","title":""},{"content":"","href":"/authors/","title":"Authors"},{"content":"","href":"/categories/","title":"Categories"},{"content":"","href":"/page/","title":"Pages"},{"content":"","href":"/series/","title":"Series"},{"content":"","href":"/tags/","title":"Tags"},{"content":"","href":"/tags/intro/","title":"intro"},{"content":"","href":"/authors/zsailer/","title":"zsailer"}]
